multiai/__init__.py
multiai/__main__.py
multiai/entry.py
multiai/multiai.py
multiai/printlong.py
multiai/data/system.ini
multiai-1.5.0.dist-info/licenses/LICENSE
multiai-1.5.0.dist-info/METADATA
multiai-1.5.0.dist-info/WHEEL
multiai-1.5.0.dist-info/entry_points.txt
multiai-1.5.0.dist-info/top_level.txt
multiai-1.5.0.dist-info/RECORD
