Metadata-Version: 2.4
Name: multiai
Version: 1.5.0
Summary: A Python library for text-based AI interactions with multi-provider support
Author: Katsutoshi Seki
License: MIT
Project-URL: Homepage, https://sekika.github.io/multiai/
Project-URL: Documentation, https://sekika.github.io/multiai/
Project-URL: Source, https://github.com/sekika/multiai
Keywords: AI
Classifier: Development Status :: 5 - Production/Stable
Classifier: Intended Audience :: Developers
Classifier: Intended Audience :: Science/Research
Classifier: Environment :: Console
Classifier: Programming Language :: Python
Classifier: Programming Language :: Python :: 3
Classifier: Programming Language :: Python :: 3.10
Classifier: Programming Language :: Python :: 3.11
Classifier: Programming Language :: Python :: 3.12
Classifier: Programming Language :: Python :: 3.13
Classifier: Programming Language :: Python :: 3.14
Classifier: License :: OSI Approved :: MIT License
Classifier: Operating System :: OS Independent
Classifier: Operating System :: MacOS :: MacOS X
Classifier: Operating System :: Microsoft :: Windows :: Windows 10
Classifier: Operating System :: Microsoft :: Windows :: Windows 11
Classifier: Operating System :: POSIX
Classifier: Operating System :: POSIX :: BSD
Classifier: Operating System :: POSIX :: Linux
Classifier: Topic :: Software Development :: Libraries :: Python Modules
Classifier: Topic :: Scientific/Engineering :: Artificial Intelligence
Classifier: Natural Language :: English
Requires-Python: >=3.10
License-File: LICENSE
Requires-Dist: openai
Requires-Dist: anthropic
Requires-Dist: google-genai
Requires-Dist: requests
Requires-Dist: mistralai
Requires-Dist: ollama
Requires-Dist: pypager
Requires-Dist: pyperclip
Requires-Dist: pypdf
Requires-Dist: trafilatura
Requires-Dist: python-docx
Dynamic: license-file
